quart_bcrypt/__init__.py
quart_bcrypt/core.py
quart_bcrypt/helpers.py
quart_bcrypt/py.typed
quart_bcrypt-0.0.9.dist-info/LICENSE
quart_bcrypt-0.0.9.dist-info/METADATA
quart_bcrypt-0.0.9.dist-info/WHEEL
quart_bcrypt-0.0.9.dist-info/RECORD
